odoo10_addon_mrp_bom_current_stock-10.0.1.0.0-py2.7-nspkg.pth
odoo/addons/mrp_bom_current_stock/README.rst
odoo/addons/mrp_bom_current_stock/__init__.py
odoo/addons/mrp_bom_current_stock/__manifest__.py
odoo/addons/mrp_bom_current_stock/reports/report_mrpcurrentstock.xml
odoo/addons/mrp_bom_current_stock/static/description/icon.png
odoo/addons/mrp_bom_current_stock/wizard/__init__.py
odoo/addons/mrp_bom_current_stock/wizard/bom_route_current_stock.py
odoo/addons/mrp_bom_current_stock/wizard/bom_route_current_stock_view.xml
odoo10_addon_mrp_bom_current_stock-10.0.1.0.0.dist-info/DESCRIPTION.rst
odoo10_addon_mrp_bom_current_stock-10.0.1.0.0.dist-info/METADATA
odoo10_addon_mrp_bom_current_stock-10.0.1.0.0.dist-info/RECORD
odoo10_addon_mrp_bom_current_stock-10.0.1.0.0.dist-info/WHEEL
odoo10_addon_mrp_bom_current_stock-10.0.1.0.0.dist-info/metadata.json
odoo10_addon_mrp_bom_current_stock-10.0.1.0.0.dist-info/namespace_packages.txt
odoo10_addon_mrp_bom_current_stock-10.0.1.0.0.dist-info/top_level.txt
